epsilon_code/__init__.py
epsilon_code/code-gen.py
epsilon_code/debug.py
epsilon_code/epcode.py
epsilon_code-1.4.0.data/scripts/epsilon.sh
epsilon_code-1.4.0.dist-info/LICENSE
epsilon_code-1.4.0.dist-info/METADATA
epsilon_code-1.4.0.dist-info/WHEEL
epsilon_code-1.4.0.dist-info/top_level.txt
epsilon_code-1.4.0.dist-info/RECORD
