Metadata-Version: 2.1
Name: epsilon-code
Version: 1.4.0
Summary: Generate and Debug Python code from the Command Line!
Home-page: https://epsilon.shreenabh.com/
Author: Shreenabh Agrawal
Author-email: me@shreenabh.com
License: UNKNOWN
Platform: UNKNOWN
Classifier: Programming Language :: Python :: 3
Classifier: License :: OSI Approved :: MIT License
Classifier: Operating System :: OS Independent
Requires-Python: >=3.6
Requires-Dist: openai
Requires-Dist: yapf
